<Properties StartupConfiguration="{644EEC18-D2E5-41C7-8497-E5EF860CE994}|Default">
  <MonoDevelop.Ide.Workbench ActiveDocument="ExampleHome/Program.cs">
    <Files>
      <File FileName="ExampleHome/Program.cs" Line="1" Column="1" />
    </Files>
    <Pads>
      <Pad Id="ProjectPad">
        <State name="__root__">
          <Node name="ExampleHome" expanded="True">
            <Node name="ExampleHome" expanded="True">
              <Node name="Program.cs" selected="True" />
            </Node>
          </Node>
        </State>
      </Pad>
    </Pads>
  </MonoDevelop.Ide.Workbench>
  <MonoDevelop.Ide.DebuggingService.PinnedWatches />
  <MonoDevelop.Ide.Workspace ActiveConfiguration="Debug|anycpu" />
  <MonoDevelop.Ide.DebuggingService.Breakpoints>
    <BreakpointStore />
  </MonoDevelop.Ide.DebuggingService.Breakpoints>
  <MultiItemStartupConfigurations />
  <MonoDevelop.Ide.ItemProperties.ExampleHome FirstBuild="True" PreferredExecutionTarget="MonoDevelop.Default" />
</Properties>